[{"head": "Cadmium chloride", "head_type": "thing", "relation": "hasCharacteristic", "tail": "white", "tail_type": "color"}, {"head": "Cadmium chloride", "head_type": "thing", "relation": "hasCharacteristic", "tail": "crystalline", "tail_type": "characteristic"}, {"head": "Cadmium chloride", "head_type": "thing", "relation": "hasCharacteristic", "tail": "hygroscopic", "tail_type": "characteristic"}, {"head": "Cadmium chloride", "head_type": "thing", "relation": "hasCharacteristic", "tail": "highly soluble in water", "tail_type": "characteristic"}, {"head": "Cadmium chloride", "head_type": "thing", "relation": "hasCharacteristic", "tail": "slightly soluble in alcohol", "tail_type": "characteristic"}, {"head": "Cadmium chloride", "head_type": "thing", "relation": "hasCharacteristic", "tail": "ionic", "tail_type": "characteristic"}, {"head": "Cadmium chloride", "head_type": "thing", "relation": "hasCharacteristic", "tail": "covalent character", "tail_type": "characteristic"}, {"head": "Cadmium chloride", "head_type": "thing", "relation": "hasCharacteristic", "tail": "bonding", "tail_type": "characteristic"}, {"head": "Cadmium chloride", "head_type": "thing", "relation": "hasCharacteristic", "tail": "crystal structure", "tail_type": "characteristic"}, {"head": "Cadmium chloride", "head_type": "thing", "relation": "hasCharacteristic", "tail": "two-dimensional layers of ions", "tail_type": "characteristic"}, {"head": "Cadmium chloride", "head_type": "thing", "relation": "hasCharacteristic", "tail": "reference", "tail_type": "characteristic"}, {"head": "Cadmium chloride", "head_type": "thing", "relation": "hasCharacteristic", "tail": "other crystal structures", "tail_type": "characteristic"}, {"head": "Cadmium chloride", "head_type": "thing", "relation": "hasMeasurement", "tail": "CdCl", "tail_type": "measurement"}, {"head": "Cadmium chloride", "head_type": "thing", "relation": "hasMeasurement", "tail": "CdCl\u2022HO", "tail_type": "measurement"}, {"head": "Cadmium chloride", "head_type": "thing", "relation": "hasMeasurement", "tail": "CdCl\u20225HO", "tail_type": "measurement"}]