[{"head": "Nathan Jonas Jordison", "head_type": "person", "relation": "hasNickname", "tail": "Joey", "tail_type": "person"}, {"head": "Nathan Jonas Jordison", "head_type": "person", "relation": "hasBirthDate", "tail": "April 26, 1975", "tail_type": "person"}, {"head": "Nathan Jonas Jordison", "head_type": "person", "relation": "isKnownFor", "tail": "work as the former drummer and co-songwriter for the American heavy metal band Slipknot", "tail_type": "creativeWork"}, {"head": "Nathan Jonas Jordison", "head_type": "person", "relation": "isKnownFor", "tail": "guitarist in the American horror punk band Murderdolls", "tail_type": "creativeWork"}, {"head": "Nathan Jonas Jordison", "head_type": "person", "relation": "isFounderOf", "tail": "Scar the Martyr", "tail_type": "creativeWork"}, {"head": "Nathan Jonas Jordison", "head_type": "person", "relation": "hasOrigin", "tail": "Waukee, Iowa", "tail_type": "place"}, {"head": "Nathan Jonas Jordison", "head_type": "person", "relation": "hasParent", "tail": "parents and two sisters", "tail_type": "person"}, {"head": "Nathan Jonas Jordison", "head_type": "person", "relation": "hasFirstInstrument", "tail": "drum kit", "tail_type": "thing"}, {"head": "Nathan Jonas Jordison", "head_type": "person", "relation": "hasAge", "tail": "8", "tail_type": "person"}, {"head": "Nathan Jonas Jordison", "head_type": "person", "relation": "hasMembership", "tail": "The Pale Ones", "tail_type": "creativeWork"}, {"head": "Nathan Jonas Jordison", "head_type": "person", "relation": "hasMembership", "tail": "Slipknot", "tail_type": "creativeWork"}, {"head": "Nathan Jonas Jordison", "head_type": "person", "relation": "hasMembership", "tail": "Scar the Martyr", "tail_type": "creativeWork"}, {"head": "Nathan Jonas Jordison", "head_type": "person", "relation": "hasPosition", "tail": "drummer", "tail_type": "person"}, {"head": "Nathan Jonas Jordison", "head_type": "person", "relation": "hasPosition", "tail": "co-songwriter", "tail_type": "person"}, {"head": "Nathan Jonas Jordison", "head_type": "person", "relation": "hasPosition", "tail": "guitarist", "tail_type": "person"}]