[{"head": "Pikkme Cool Golden Black Abstract Pattern Designer Printed Hard Back Covers and Cases", "head_type": "product", "relation": "isProducedBy", "tail": "Pikkme", "tail_type": "manufacturer"}, {"head": "Pikkme Cool Golden Black Abstract Pattern Designer Printed Hard Back Covers and Cases", "head_type": "product", "relation": "hasCharacteristic", "tail": "Cutting edge sublimation printing technology", "tail_type": "characteristic"}, {"head": "Pikkme Cool Golden Black Abstract Pattern Designer Printed Hard Back Covers and Cases", "head_type": "product", "relation": "hasCharacteristic", "tail": "Polymer", "tail_type": "material"}, {"head": "Pikkme Cool Golden Black Abstract Pattern Designer Printed Hard Back Covers and Cases", "head_type": "product", "relation": "hasCharacteristic", "tail": "Very colorful design", "tail_type": "characteristic"}, {"head": "Pikkme Cool Golden Black Abstract Pattern Designer Printed Hard Back Covers and Cases", "head_type": "product", "relation": "hasMeasurement", "tail": "Samsung Galaxy M12 / F12", "tail_type": "measurement"}, {"head": "Pikkme Cool Golden Black Abstract Pattern Designer Printed Hard Back Covers and Cases", "head_type": "product", "relation": "hasMeasurement", "tail": "One-year warranty", "tail_type": "measurement"}, {"head": "Pikkme Cool Golden Black Abstract Pattern Designer Printed Hard Back Covers and Cases", "head_type": "product", "relation": "hasMeasurement", "tail": "Worldwide delivery", "tail_type": "measurement"}]