[{"head": "Funny Dog Mama Life is Ruff Ladies Triblend Dolman Tee", "head_type": "product", "relation": "hasColor", "tail": "Turquoise", "tail_type": "color"}, {"head": "Funny Dog Mama Life is Ruff Ladies Triblend Dolman Tee", "head_type": "product", "relation": "hasMeasurement", "tail": "Large", "tail_type": "measurement"}, {"head": "Funny Dog Mama Life is Ruff Ladies Triblend Dolman Tee", "head_type": "product", "relation": "hasCharacteristic", "tail": "Slightly fitted modern styling", "tail_type": "characteristic"}, {"head": "Funny Dog Mama Life is Ruff Ladies Triblend Dolman Tee", "head_type": "product", "relation": "hasCharacteristic", "tail": "Variety of colors", "tail_type": "characteristic"}, {"head": "Funny Dog Mama Life is Ruff Ladies Triblend Dolman Tee", "head_type": "product", "relation": "hasCharacteristic", "tail": "Large range of sizes", "tail_type": "characteristic"}, {"head": "Funny Dog Mama Life is Ruff Ladies Triblend Dolman Tee", "head_type": "product", "relation": "hasCharacteristic", "tail": "Sarcastic, novelty, punny, or slightly offensive", "tail_type": "characteristic"}]