[{"head": "TEXTILE BOOST Women's Jacquard Saree", "head_type": "product", "relation": "isProducedBy", "tail": "TEXTILE BOOST", "tail_type": "manufacturer"}, {"head": "TEXTILE BOOST Women's Jacquard Saree", "head_type": "product", "relation": "madeOfMaterial", "tail": "Jacquard Material", "tail_type": "material"}, {"head": "TEXTILE BOOST Women's Jacquard Saree", "head_type": "product", "relation": "hasMeasurement", "tail": "5.5 meter Saree", "tail_type": "measurement"}, {"head": "TEXTILE BOOST Women's Jacquard Saree", "head_type": "product", "relation": "hasMeasurement", "tail": "0.80 meter Blouse piece", "tail_type": "measurement"}, {"head": "TEXTILE BOOST Women's Jacquard Saree", "head_type": "product", "relation": "hasColor", "tail": "Pink", "tail_type": "color"}, {"head": "Jacquard Material", "head_type": "material", "relation": "hasCharacteristic", "tail": "sheer", "tail_type": "characteristic"}, {"head": "Jacquard Material", "head_type": "material", "relation": "hasCharacteristic", "tail": "lightweight", "tail_type": "characteristic"}, {"head": "Jacquard Material", "head_type": "material", "relation": "hasCharacteristic", "tail": "dull-finished", "tail_type": "characteristic"}, {"head": "Jacquard Material", "head_type": "material", "relation": "hasCharacteristic", "tail": "clingy and flowing look", "tail_type": "characteristic"}, {"head": "Jacquard Material", "head_type": "material", "relation": "hasCharacteristic", "tail": "drapes well", "tail_type": "characteristic"}, {"head": "TEXTILE BOOST Women's Jacquard Saree", "head_type": "product", "relation": "hasCharacteristic", "tail": "bright colour", "tail_type": "characteristic"}, {"head": "TEXTILE BOOST Women's Jacquard Saree", "head_type": "product", "relation": "hasCharacteristic", "tail": "prints", "tail_type": "characteristic"}]